[{"line":2,"elements":[{"start_timestamp":"2022-12-15T07:29:20.607Z","line":4,"name":"Gecerli Datalarla Giris Yapma","description":"","id":"login;gecerli-datalarla-giris-yapma","type":"scenario","keyword":"Scenario","steps":[{"result":{"status":"undefined"},"line":5,"name":"Kullanici gecerli datalarla request yapar","match":{},"keyword":"Given "},{"result":{"duration":500800,"status":"skipped"},"line":6,"name":"Kullanici status code 200 oldugunu dogrular","match":{},"keyword":"Then "}],"tags":[{"name":"@login"}]}],"name":"Login","description":"","id":"login","keyword":"Feature","uri":"file:src/test/resources/features/Login.feature","tags":[{"name":"@login","type":"Tag","location":{"line":1,"column":1}}]}]